mrcs/__init__.py
mrcs/client.py
mrcs/constants.py
mrcs/prefix_bot.py
mrcs/user.py
mrcs-0.1.4.dist-info/METADATA
mrcs-0.1.4.dist-info/WHEEL
mrcs-0.1.4.dist-info/top_level.txt
mrcs-0.1.4.dist-info/RECORD
