Metadata-Version: 2.1
Name: mrcs
Version: 0.1.4
Summary: A library to create bots for MRCS (custom msgroom server)
Author-email: GEOEGII555 <geoegii2001555@gmail.com>
Project-URL: Homepage, https://github.com/GEOEGII555/mrcs.py
Project-URL: Bug Tracker, https://github.com/GEOEGII555/mrcs.py/issues
Classifier: Programming Language :: Python :: 3
Classifier: Operating System :: OS Independent
Requires-Python: >=3.7
Requires-Dist: python-socketio >=5.9.0
Requires-Dist: websocket-client
